reparo/CDI.py
reparo/FRNNI.py
reparo/HotDeckImputation.py
reparo/KNNImputer.py
reparo/MICE.py
reparo/PMM.py
reparo/SICE.py
reparo/__init__.py
reparo/errors.py
reparo-0.0.6.dist-info/METADATA
reparo-0.0.6.dist-info/WHEEL
reparo-0.0.6.dist-info/top_level.txt
reparo-0.0.6.dist-info/RECORD
