Metadata-Version: 2.1
Name: reparo
Version: 0.0.6
Summary: Reparo is a python sci-kit learn inspired package for Missing Value Imputation.
Home-page: https://github.com/SigmoidAI/reparo
Author: SigmoidAI - Stojoc Vladimir
Author-email: vladimir.stojoc@gmail.com
License: MIT
Download-URL: https://github.com/ScienceKot/kydavra/archive/v1.0.tar.gz
Keywords: ml,machine learning,feature engineering,python,data science
Platform: UNKNOWN
Classifier: Development Status :: 3 - Alpha
Classifier: Framework :: Jupyter
Classifier: Intended Audience :: Science/Research
Classifier: Topic :: Scientific/Engineering :: Artificial Intelligence
Classifier: Topic :: Scientific/Engineering :: Mathematics
Classifier: Topic :: Software Development :: Libraries :: Python Modules
Classifier: Topic :: Software Development :: Build Tools
Classifier: License :: OSI Approved :: MIT License
Classifier: Programming Language :: Python :: 3
Classifier: Programming Language :: Python :: 3.4
Classifier: Programming Language :: Python :: 3.5
Classifier: Programming Language :: Python :: 3.6
Classifier: Programming Language :: Python :: 3.7
Classifier: Programming Language :: Python :: 3.8
Classifier: Programming Language :: Python :: 3.9
Classifier: Programming Language :: Python :: 3.10
Classifier: Programming Language :: Python :: 3.11
Requires-Dist: numpy
Requires-Dist: pandas
Requires-Dist: scikit-learn
Requires-Dist: statsmodels
